groia/__init__.py
groia/groia.py
groia-0.1.0.dist-info/entry_points.txt
groia-0.1.0.dist-info/WHEEL
groia-0.1.0.dist-info/METADATA
groia-0.1.0.dist-info/RECORD
