Metadata-Version: 2.3
Name: groia
Version: 0.1.0
Summary: Um bot para gerar mensagens de forma agressiva
Keywords: linguagem agressiva,mensagens
Author-email: MikaVirus <mikavirus.adm@gmail.com>
Classifier: Programming Language :: Python :: 3
Classifier: License :: OSI Approved :: MIT License
Classifier: Operating System :: OS Independent
Requires-Dist: requests
Requires-Dist: pytz
